fastapi_admin/__init__.py
fastapi_admin/_version.py
fastapi_admin/cli.py
fastapi_admin/commands/__init__.py
fastapi_admin/commands/app.py
fastapi_admin/commands/migrations.py
fastapi_admin/commands/project.py
fastapi_admin/commands/server.py
fastapi_admin/utils/__init__.py
fastapi_admin/utils/file_utils.py
fastapi_admin/utils/git_utils.py
fastapi_admin/utils/template_utils.py
fastapi_admin_cli-0.4.5.dist-info/licenses/LICENSE
scripts/__init__.py
scripts/create_template_structure.py
fastapi_admin_cli-0.4.5.dist-info/METADATA
fastapi_admin_cli-0.4.5.dist-info/WHEEL
fastapi_admin_cli-0.4.5.dist-info/entry_points.txt
fastapi_admin_cli-0.4.5.dist-info/top_level.txt
fastapi_admin_cli-0.4.5.dist-info/RECORD
