Metadata-Version: 2.4
Name: fastapi-admin-cli
Version: 0.4.5
Summary: Django-inspired CLI for FastAPI applications
Author-email: Amal Babu <developer.amalbabu@gmail.com>
License-Expression: MIT
Project-URL: Homepage, https://github.com/amal-babu-git/fastapi-admin-cli
Project-URL: Bug Tracker, https://github.com/amal-babu-git/fastapi-admin-cli/issues
Classifier: Programming Language :: Python :: 3
Classifier: Programming Language :: Python :: 3.8
Classifier: Programming Language :: Python :: 3.9
Classifier: Programming Language :: Python :: 3.10
Classifier: Programming Language :: Python :: 3.11
Classifier: Operating System :: OS Independent
Classifier: Intended Audience :: Developers
Classifier: Topic :: Software Development :: Libraries :: Python Modules
Requires-Python: >=3.8
License-File: LICENSE
Requires-Dist: typer>=0.4.0
Requires-Dist: jinja2>=3.0.0
Requires-Dist: uvicorn>=0.15.0
Requires-Dist: toml>=0.10.2
Requires-Dist: gitpython>=3.1.30
Provides-Extra: dev
Requires-Dist: pytest>=7.0.0; extra == "dev"
Requires-Dist: black>=23.0.0; extra == "dev"
Requires-Dist: ruff>=0.0.292; extra == "dev"
Requires-Dist: build>=0.10.0; extra == "dev"
Requires-Dist: twine>=4.0.0; extra == "dev"
Requires-Dist: toml>=0.10.2; extra == "dev"
Dynamic: license-file
Dynamic: requires-python
